kingery_bulmash/__about__.py
kingery_bulmash/__init__.py
kingery_bulmash/kingery_bulmash.py
kingery_bulmash-1.0.1.dist-info/METADATA
kingery_bulmash-1.0.1.dist-info/WHEEL
kingery_bulmash-1.0.1.dist-info/licenses/LICENSE
kingery_bulmash-1.0.1.dist-info/RECORD
