Metadata-Version: 2.3
Name: kingery-bulmash
Version: 1.0.1
Summary: Kingery-Bulmash Blast Wave Characteristics Calculator
Project-URL: Homepage, https://github.com/fcento100/kingery-bulmash
Project-URL: Issues, https://github.com/fcento100/kingery-bulmash/issues
Author: fcento100
License: MIT License
License-File: LICENSE
Keywords: TNT,blast,bulmash,kingery
Classifier: Intended Audience :: Science/Research
Classifier: License :: OSI Approved :: MIT License
Classifier: Operating System :: OS Independent
Classifier: Programming Language :: Python :: 3
Classifier: Programming Language :: Python :: 3.12
Classifier: Topic :: Scientific/Engineering
Requires-Python: >=3.12
